tap_mysql/__init__.py
tap_mysql/connection.py
tap_mysql/discover_utils.py
tap_mysql/stream_utils.py
tap_mysql/sync_strategies/__init__.py
tap_mysql/sync_strategies/binlog.py
tap_mysql/sync_strategies/common.py
tap_mysql/sync_strategies/full_table.py
tap_mysql/sync_strategies/incremental.py
pipelinewise_tap_mysql-1.6.0.dist-info/LICENSE
pipelinewise_tap_mysql-1.6.0.dist-info/METADATA
pipelinewise_tap_mysql-1.6.0.dist-info/WHEEL
pipelinewise_tap_mysql-1.6.0.dist-info/entry_points.txt
pipelinewise_tap_mysql-1.6.0.dist-info/top_level.txt
pipelinewise_tap_mysql-1.6.0.dist-info/RECORD
