Metadata-Version: 2.1
Name: pipelinewise-tap-mysql
Version: 1.6.0
Summary: Singer.io tap for extracting data from MySQL & MariaDB - PipelineWise compatible
Home-page: https://github.com/transferwise/pipelinewise-tap-mysql
Author: Wise
Classifier: License :: OSI Approved :: GNU Affero General Public License v3
Classifier: Programming Language :: Python :: 3 :: Only
License-File: LICENSE
Requires-Dist: pendulum ==2.1.2
Requires-Dist: pipelinewise-singer-python ==1.*
Requires-Dist: mysql-replication ==0.43
Requires-Dist: PyMySQL ==1.1.*
Requires-Dist: plpygis ==0.2.1
Requires-Dist: tzlocal ==2.1
Provides-Extra: test
Requires-Dist: nose ==1.3.* ; extra == 'test'
Requires-Dist: pylint ==2.13.2 ; extra == 'test'
Requires-Dist: nose-cov ==1.6 ; extra == 'test'
